{
	"id": "78bcc472-46f9-4b3a-ade5-14bac16766aa",
	"name": "[LAN] - Hikvision DS-7104NI-Q1 / 4P NVR",
	"values": [
		{
			"key": "NVR_USERNAME",
			"value": "",
			"type": "secret",
			"enabled": true
		},
		{
			"key": "NVR_PASSWORD",
			"value": "",
			"type": "secret",
			"enabled": true
		},
		{
			"key": "NVR_HOSTNAME",
			"value": "",
			"type": "default",
			"enabled": true
		},
		{
			"key": "NVR_PORT",
			"value": "",
			"type": "default",
			"enabled": true
		},
		{
			"key": "NVR_PROTOCOL",
			"value": "",
			"type": "default",
			"enabled": true
		}
	],
	"_postman_variable_scope": "environment",
	"_postman_exported_at": "2024-10-12T02:53:24.567Z",
	"_postman_exported_using": "Postman/11.16.1"
}